MANIFEST.in
README.txt
setup.py
Products/__init__.py
Products.cron4plone.egg-info/PKG-INFO
Products.cron4plone.egg-info/SOURCES.txt
Products.cron4plone.egg-info/dependency_links.txt
Products.cron4plone.egg-info/entry_points.txt
Products.cron4plone.egg-info/namespace_packages.txt
Products.cron4plone.egg-info/not-zip-safe
Products.cron4plone.egg-info/requires.txt
Products.cron4plone.egg-info/top_level.txt
Products/cron4plone/__init__.py
Products/cron4plone/config.py
Products/cron4plone/configure.zcml
Products/cron4plone/interfaces.py
Products/cron4plone/profiles.zcml
Products/cron4plone/rebuild_i18n.sh
Products/cron4plone/setuphandlers.py
Products/cron4plone/tool.gif
Products/cron4plone/upgrades.py
Products/cron4plone/upgrades.zcml
Products/cron4plone/browser/__init__.py
Products/cron4plone/browser/configure.zcml
Products/cron4plone/browser/configlets/__init__.py
Products/cron4plone/browser/configlets/cron_configuration.py
Products/cron4plone/browser/images/clock.png
Products/cron4plone/browser/views/__init__.py
Products/cron4plone/browser/views/cron_tick.py
Products/cron4plone/locales/Products.cron4plone.pot
Products/cron4plone/locales/en/LC_MESSAGES/Products.cron4plone.po
Products/cron4plone/locales/nl/LC_MESSAGES/Products.cron4plone.po
Products/cron4plone/profiles/default/Products.cron4plone_various.txt
Products/cron4plone/profiles/default/actionicons.xml
Products/cron4plone/profiles/default/controlpanel.xml
Products/cron4plone/profiles/default/import_steps.xml
Products/cron4plone/profiles/default/metadata.xml
Products/cron4plone/profiles/default/toolset.xml
Products/cron4plone/tests/__init__.py
Products/cron4plone/tests/base.py
Products/cron4plone/tests/cron4plone.txt
Products/cron4plone/tests/test_setup.py
Products/cron4plone/tools/__init__.py
Products/cron4plone/tools/configlet_util.py
Products/cron4plone/tools/crontab_utils.py
Products/cron4plone/tools/crontool.py
docs/HISTORY.txt
docs/INSTALL.txt
docs/LICENSE.GPL
docs/LICENSE.txt