Metadata-Version: 1.0
Name: Products.cron4plone
Version: 1.1.11
Summary: cron4plone can do scheduled tasks in Plone
Home-page: http://www.gw20e.com/
Author: Goldmund, Wyldebeast & Wunderliebe
Author-email: info@gw20e.com
License: GPL
Keywords: crontab plone cron scheduling
Platform: UNKNOWN
Classifier: Framework :: Plone
Classifier: Programming Language :: Python
Classifier: Topic :: Software Development :: Libraries :: Python Modules
